bumpversion/__init__.py
bumpversion/__main__.py
bumpversion/cli.py
bumpversion/exceptions.py
bumpversion/functions.py
bumpversion/utils.py
bumpversion/vcs.py
bumpversion/version_part.py
bump2version-1.0.0.dist-info/LICENSE.rst
bump2version-1.0.0.dist-info/METADATA
bump2version-1.0.0.dist-info/WHEEL
bump2version-1.0.0.dist-info/entry_points.txt
bump2version-1.0.0.dist-info/top_level.txt
bump2version-1.0.0.dist-info/RECORD
